LICENSE
serotiny/__init__.py
serotiny/cli/__init__.py
serotiny/cli/_utils/__init__.py
serotiny/cli/_utils/pipeline_cli.py
serotiny/cli/cli.py
serotiny/cli/dataframe_cli/__init__.py
serotiny/cli/dataframe_cli/transform.py
serotiny/dataframe/__init__.py
serotiny/dataframe/readers.py
serotiny/dataframe/transforms/__init__.py
serotiny/dataframe/transforms/filter.py
serotiny/dataframe/transforms/group_cols.py
serotiny/dataframe/transforms/misc.py
serotiny/dataframe/transforms/split.py
serotiny/datamodules/__init__.py
serotiny/datamodules/dataframe/__init__.py
serotiny/datamodules/dataframe/dataframe_datamodule.py
serotiny/datamodules/dataframe/utils.py
serotiny/image/io/__init__.py
serotiny/image/io/monai_bio_reader.py
serotiny/image/transforms/__init__.py
serotiny/image/transforms/bright_sampler.py
serotiny/image/transforms/multiscale_cropper.py
serotiny/image/transforms/resize.py
serotiny/loggers/__init__.py
serotiny/loggers/mlflow.py
serotiny/models/__init__.py
serotiny/models/base_model.py
serotiny/models/basic_model.py
serotiny/models/utils/__init__.py
serotiny/models/utils/mlflow.py
serotiny/nn/__init__.py
serotiny/nn/losses/__init__.py
serotiny/nn/losses/adversarial_loss.py
serotiny/nn/losses/continuous_bernoulli.py
serotiny/nn/losses/cosine_loss.py
serotiny/nn/losses/gaussian_nllloss.py
serotiny/nn/losses/weibull.py
serotiny/tests/test_mlflow_logger.py
serotiny-1.0.1.dist-info/entry_points.txt
serotiny-1.0.1.dist-info/WHEEL
serotiny-1.0.1.dist-info/METADATA
serotiny-1.0.1.dist-info/licenses/LICENSE
serotiny-1.0.1.dist-info/RECORD
